caproto_sandbox/__init__.py
caproto_sandbox/_version.py
caproto_sandbox/device_simple_gui.py
caproto_sandbox/io_device_client.py
caproto_sandbox/io_device_gui.py
caproto_sandbox/io_device_server.py
caproto_sandbox/io_interupt_gui.py
caproto_sandbox/io_interupt_server.py
caproto_sandbox/plane_random_walk_client.py
caproto_sandbox/random_walk_gui.py
caproto_sandbox/random_walk_modified.py
caproto_sandbox/random_walk_modified_gui.py
caproto_sandbox/server.py
caproto_sandbox/simple_device.py
caproto_sandbox/simple_device_client.py
caproto_sandbox/simple_device_gui.py
caproto_sandbox/simple_server.py
caproto_sandbox/simple_server0.py
caproto_sandbox/worker_thread_pc.py
caproto_sandbox/tests/__init__.py
caproto_sandbox/tests/conftest.py
caproto_sandbox/tests/test_examples.py
caproto_sandbox-0.0.0.dist-info/AUTHORS.rst
caproto_sandbox-0.0.0.dist-info/LICENSE
caproto_sandbox-0.0.0.dist-info/METADATA
caproto_sandbox-0.0.0.dist-info/WHEEL
caproto_sandbox-0.0.0.dist-info/entry_points.txt
caproto_sandbox-0.0.0.dist-info/top_level.txt
caproto_sandbox-0.0.0.dist-info/RECORD
