Metadata-Version: 2.1
Name: caproto-sandbox
Version: 0.0.0
Summary: Testground for caproto and pyepics
Home-page: https://github.com/vstadnytskyi/caproto-sandbox
Author: Valentyn Stadnytskyi
Author-email: v.stadnytskyi@gmail.com
License: BSD (3-clause)
Platform: UNKNOWN
Classifier: Development Status :: 2 - Pre-Alpha
Classifier: Natural Language :: English
Classifier: Programming Language :: Python :: 3
Requires-Python: >=3.6
